even_odd_pip/__init__.py
even_odd_pip/odd_even_check.py
even_odd_pip/version.py
even_odd_pip-0.0.1.dist-info/licenses/LICENSE
even_odd_pip-0.0.1.dist-info/METADATA
even_odd_pip-0.0.1.dist-info/WHEEL
even_odd_pip-0.0.1.dist-info/top_level.txt
even_odd_pip-0.0.1.dist-info/RECORD
